goat/__init__.py
goat/classes/plugin_base.py
goat/classes/tool_base.py
goat/classes/wallet_client_base.py
goat/decorators/tool.py
goat/types/chain.py
goat/utils/get_tools.py
goat/utils/snake_case.py
goat_sdk-0.1.6.dist-info/METADATA
goat_sdk-0.1.6.dist-info/WHEEL
goat_sdk-0.1.6.dist-info/RECORD
