Metadata-Version: 2.1
Name: goat-sdk
Version: 0.1.6
Summary: Goat 🐐 (Great Onchain Agent Toolkit) is an open-source framework for connecting AI agents to any onchain app
Home-page: https://ohmygoat.dev/
Keywords: goat,sdk,web3,agents,ai
Author: Andrea Villa
Author-email: andreakarimodm@gmail.com
Requires-Python: >=3.10,<4.0
Classifier: Programming Language :: Python :: 3
Classifier: Programming Language :: Python :: 3.10
Classifier: Programming Language :: Python :: 3.11
Classifier: Programming Language :: Python :: 3.12
Requires-Dist: asyncio (>=3.4.1,<4.0.0)
Requires-Dist: pydantic (>=2.0.0,<3.0.0)
Requires-Dist: typing-extensions (>=4.12.2,<5.0.0)
Project-URL: Bug Tracker, https://github.com/goat-sdk/goat/issues
Project-URL: Repository, https://github.com/goat-sdk/goat
